lastplayer/__init__.py
lastplayer-0.0.1.data/scripts/lastplayer
lastplayer-0.0.1.dist-info/METADATA
lastplayer-0.0.1.dist-info/RECORD
lastplayer-0.0.1.dist-info/WHEEL
lastplayer-0.0.1.dist-info/top_level.txt
