Metadata-Version: 2.1
Name: lastplayer
Version: 0.0.1
Summary: Simple program that keeps the order of the last used players
Home-page: https://github.com/ricede/lastplayer
Author: Tudor Roman
Author-email: tudurom@gmail.com
License: UNKNOWN
Platform: UNKNOWN
Classifier: Programming Language :: Python :: 3
Classifier: License :: OSI Approved :: ISC License (ISCL)
Classifier: Operating System :: POSIX
Classifier: Topic :: Desktop Environment
Requires-Python: >=3.5
Requires-Dist: PyGObject
Requires-Dist: dbus-python
